toy_python_package/__init__.py
toy_python_package/toy_python_package.py
toy_python_package-0.1.0.dist-info/LICENSE
toy_python_package-0.1.0.dist-info/WHEEL
toy_python_package-0.1.0.dist-info/METADATA
toy_python_package-0.1.0.dist-info/RECORD
